<?xml version="1.0" encoding="GB2312"?>

<data>
  <row>
    <CSID>1.0</CSID>
    <XH>2.0</XH>
    <NAME>1Color</NAME>
    <VALUE>#FFFF00</VALUE>
    <SM></SM>
  </row>
  <row>
    <CSID>1.0</CSID>
    <XH>3.0</XH>
    <NAME>2Color</NAME>
    <VALUE>#FF6300</VALUE>
    <SM></SM>
  </row>
  <row>
    <CSID>1.0</CSID>
    <XH>4.0</XH>
    <NAME>3Color</NAME>
    <VALUE>#F000FF</VALUE>
    <SM></SM>
  </row>
  <row>
    <CSID>1.0</CSID>
    <XH>5.0</XH>
    <NAME>4Color</NAME>
    <VALUE>#E0FF00</VALUE>
    <SM></SM>
  </row>
  <row>
    <CSID>1.0</CSID>
    <XH>6.0</XH>
    <NAME>y_type</NAME>
    <VALUE>i</VALUE>
    <SM></SM>
  </row>
  <row>
    <CSID>1.0</CSID>
    <XH>7.0</XH>
    <NAME>width</NAME>
    <VALUE>300</VALUE>
    <SM></SM>
  </row>
  <row>
    <CSID>1.0</CSID>
    <XH>8.0</XH>
    <NAME>height</NAME>
    <VALUE>150</VALUE>
    <SM></SM>
  </row>
  <row>
    <CSID>1.0</CSID>
    <XH>9.0</XH>
    <NAME>coordColor</NAME>
    <VALUE>#000000</VALUE>
    <SM></SM>
  </row>
  <row>
    <CSID>1.0</CSID>
    <XH>10.0</XH>
    <NAME>gridColor</NAME>
    <VALUE>#000000</VALUE>
    <SM></SM>
  </row>
  <row>
    <CSID>1.0</CSID>
    <XH>11.0</XH>
    <NAME>borderColor</NAME>
    <VALUE>#636363</VALUE>
    <SM></SM>
  </row>
  <row>
    <CSID>2.0</CSID>
    <XH>1.0</XH>
    <NAME>width</NAME>
    <VALUE>300</VALUE>
    <SM></SM>
  </row>
  <row>
    <CSID>1.0</CSID>
    <XH>1.0</XH>
    <NAME>bgColor</NAME>
    <VALUE>#FFFFFF</VALUE>
    <SM></SM>
  </row>
  <row>
    <CSID>2.0</CSID>
    <XH>2.0</XH>
    <NAME>height</NAME>
    <VALUE>200</VALUE>
    <SM></SM>
  </row>
  <row>
    <CSID>2.0</CSID>
    <XH>3.0</XH>
    <NAME>a</NAME>
    <VALUE>80</VALUE>
    <SM></SM>
  </row>
  <row>
    <CSID>2.0</CSID>
    <XH>4.0</XH>
    <NAME>b</NAME>
    <VALUE>60</VALUE>
    <SM></SM>
  </row>
  <row>
    <CSID>2.0</CSID>
    <XH>5.0</XH>
    <NAME>h</NAME>
    <VALUE>18</VALUE>
    <SM></SM>
  </row>
</data>
